avocado_mail_result/__init__.py
avocado_mail_result/mail_result.py
avocado_framework_plugin_mail_result-105.0.dist-info/METADATA
avocado_framework_plugin_mail_result-105.0.dist-info/WHEEL
avocado_framework_plugin_mail_result-105.0.dist-info/entry_points.txt
avocado_framework_plugin_mail_result-105.0.dist-info/top_level.txt
avocado_framework_plugin_mail_result-105.0.dist-info/RECORD
