Metadata-Version: 2.1
Name: avocado-framework-plugin-mail-result
Version: 105.0
Summary: Avocado Mail Results for Jobs
Home-page: http://avocado-framework.github.io/
Author: Avocado Developers
Author-email: avocado-devel@redhat.com
Requires-Dist: avocado-framework ==105.0
